flowshow/__init__.py
flowshow/visualize.py
flowshow/templates/index.html
flowshow-0.2.2.dist-info/METADATA
flowshow-0.2.2.dist-info/WHEEL
flowshow-0.2.2.dist-info/RECORD
