Metadata-Version: 2.4
Name: flowshow
Version: 0.2.2
Summary: A tool for visualizing nested task execution flows
Author: Vincent Warmerdam
License: MIT
Requires-Python: >=3.10
Requires-Dist: jinja2
Requires-Dist: orjson
Requires-Dist: pydantic
Requires-Dist: pytz
Requires-Dist: stamina
Provides-Extra: dev
Requires-Dist: build>=1.0.3; extra == 'dev'
Requires-Dist: pytest>=7.0.0; extra == 'dev'
Requires-Dist: ruff>=0.1.9; extra == 'dev'
Requires-Dist: twine>=4.0.2; extra == 'dev'
